aidon/__init__.py
aidon/aidon_forward.py
aidon/aidon_obis.py
aidon/aidon_temp_format.py
aidon/aidon_test.py
aidon/hass_influx.py
aidon-0.0.5.dist-info/METADATA
aidon-0.0.5.dist-info/WHEEL
aidon-0.0.5.dist-info/entry_points.txt
aidon-0.0.5.dist-info/RECORD
