Metadata-Version: 2.1
Name: aidon
Version: 0.0.5
Project-URL: Homepage, https://github.com/TrondKjeldas/meter_reading
Requires-Python: >=3.9
Requires-Dist: crcmod
Requires-Dist: pyserial
Requires-Dist: requests
